[{"resource": "playercareerstats", "parameters": {"PerMode": "Totals", "PlayerID": 1628035, "LeagueID": null}, "resultSets": [{"name": "SeasonTotalsRegularSeason", "headers": ["PLAYER_ID", "SEASON_ID", "LEAGUE_ID", "TEAM_ID", "TEAM_ABBREVIATION", "PLAYER_AGE", "GP", "GS", "MIN", "FGM", "FGA", "FG_PCT", "FG3M", "FG3A", "FG3_PCT", "FTM", "FTA", "FT_PCT", "OREB", "DREB", "REB", "AST", "STL", "BLK", "TOV", "PF", "PTS"], "rowSet": [[1628035, "2017-18", "00", 1610612761, "TOR", 25.0, 14, 0, 53.0, 8, 15, 0.533, 3, 9, 0.333, 2, 3, 0.667, 1, 6, 7, 1, 1, 1, 3, 8, 21], [1628035, "2018-19", "00", 1610612744, "GSW", 26.0, 72, 5, 1003.0, 134, 275, 0.487, 42, 118, 0.356, 27, 48, 0.563, 81, 166, 247, 31, 18, 15, 30, 134, 337], [1628035, "2019-20", "00", 1610612739, "CLE", 27.0, 40, 1, 593.0, 73, 171, 0.427, 14, 65, 0.215, 22, 31, 0.71, 37, 76, 113, 14, 23, 8, 26, 72, 182], [1628035, "2020-21", "00", 1610612747, "LAL", 28.0, 39, 0, 258.0, 48, 93, 0.516, 16, 39, 0.41, 10, 18, 0.556, 22, 32, 54, 6, 7, 0, 5, 26, 122], [1628035, "2021-22", "00", 1610612741, "CHI", 29.0, 17, 3, 206.0, 24, 61, 0.393, 9, 27, 0.333, 2, 8, 0.25, 13, 20, 33, 5, 2, 3, 7, 26, 59]]}, {"name": "CareerTotalsRegularSeason", "headers": ["PLAYER_ID", "LEAGUE_ID", "Team_ID", "GP", "GS", "MIN", "FGM", "FGA", "FG_PCT", "FG3M", "FG3A", "FG3_PCT", "FTM", "FTA", "FT_PCT", "OREB", "DREB", "REB", "AST", "STL", "BLK", "TOV", "PF", "PTS"], "rowSet": [[1628035, "00", 0, 182, 9, 2115.0, 287, 615, 0.466666, 84, 258, 0.325581, 63, 108, 0.583333, 154, 300, 454, 57, 51, 27, 71, 266, 721]]}, {"name": "SeasonTotalsPostSeason", "headers": ["PLAYER_ID", "SEASON_ID", "LEAGUE_ID", "TEAM_ID", "TEAM_ABBREVIATION", "PLAYER_AGE", "GP", "GS", "MIN", "FGM", "FGA", "FG_PCT", "FG3M", "FG3A", "FG3_PCT", "FTM", "FTA", "FT_PCT", "OREB", "DREB", "REB", "AST", "STL", "BLK", "TOV", "PF", "PTS"], "rowSet": [[1628035, "2018-19", "00", 1610612744, "GSW", 26.0, 22, 1, 235.0, 26, 59, 0.441, 10, 32, 0.313, 4, 10, 0.4, 17, 33, 50, 4, 2, 1, 6, 32, 66], [1628035, "2020-21", "00", 1610612747, "LAL", 28.0, 2, 0, 12.0, 0, 3, 0.0, 0, 2, 0.0, 0, 0, 0.0, 0, 1, 1, 0, 0, 0, 0, 1, 0]]}, {"name": "CareerTotalsPostSeason", "headers": ["PLAYER_ID", "LEAGUE_ID", "Team_ID", "GP", "GS", "MIN", "FGM", "FGA", "FG_PCT", "FG3M", "FG3A", "FG3_PCT", "FTM", "FTA", "FT_PCT", "OREB", "DREB", "REB", "AST", "STL", "BLK", "TOV", "PF", "PTS"], "rowSet": [[1628035, "00", 0, 24, 1, 247.0, 26, 62, 0.419354, 10, 34, 0.294117, 4, 10, 0.4, 17, 34, 51, 4, 2, 1, 6, 33, 66]]}, {"name": "SeasonTotalsAllStarSeason", "headers": ["PLAYER_ID", "SEASON_ID", "LEAGUE_ID", "TEAM_ID", "TEAM_ABBREVIATION", "PLAYER_AGE", "GP", "GS", "MIN", "FGM", "FGA", "FG_PCT", "FG3M", "FG3A", "FG3_PCT", "FTM", "FTA", "FT_PCT", "OREB", "DREB", "REB", "AST", "STL", "BLK", "TOV", "PF", "PTS"], "rowSet": []}, {"name": "CareerTotalsAllStarSeason", "headers": ["PLAYER_ID", "LEAGUE_ID", "Team_ID", "GP", "GS", "MIN", "FGM", "FGA", "FG_PCT", "FG3M", "FG3A", "FG3_PCT", "FTM", "FTA", "FT_PCT", "OREB", "DREB", "REB", "AST", "STL", "BLK", "TOV", "PF", "PTS"], "rowSet": []}, {"name": "SeasonTotalsCollegeSeason", "headers": ["PLAYER_ID", "SEASON_ID", "LEAGUE_ID", "ORGANIZATION_ID", "SCHOOL_NAME", "PLAYER_AGE", "GP", "GS", "MIN", "FGM", "FGA", "FG_PCT", "FG3M", "FG3A", "FG3_PCT", "FTM", "FTA", "FT_PCT", "OREB", "DREB", "REB", "AST", "STL", "BLK", "TOV", "PF", "PTS"], "rowSet": []}, {"name": "CareerTotalsCollegeSeason", "headers": ["PLAYER_ID", "LEAGUE_ID", "ORGANIZATION_ID", "GP", "GS", "MIN", "FGM", "FGA", "FG_PCT", "FG3M", "FG3A", "FG3_PCT", "FTM", "FTA", "FT_PCT", "OREB", "DREB", "REB", "AST", "STL", "BLK", "TOV", "PF", "PTS"], "rowSet": []}, {"name": "SeasonTotalsShowcaseSeason", "headers": ["PLAYER_ID", "SEASON_ID", "LEAGUE_ID", "TEAM_ID", "TEAM_ABBREVIATION", "PLAYER_AGE", "GP", "GS", "MIN", "FGM", "FGA", "FG_PCT", "FG3M", "FG3A", "FG3_PCT", "FTM", "FTA", "FT_PCT", "OREB", "DREB", "REB", "AST", "STL", "BLK", "TOV", "PF", "PTS"], "rowSet": []}, {"name": "CareerTotalsShowcaseSeason", "headers": ["PLAYER_ID", "LEAGUE_ID", "Team_ID", "GP", "GS", "MIN", "FGM", "FGA", "FG_PCT", "FG3M", "FG3A", "FG3_PCT", "FTM", "FTA", "FT_PCT", "OREB", "DREB", "REB", "AST", "STL", "BLK", "TOV", "PF", "PTS"], "rowSet": []}, {"name": "SeasonRankingsRegularSeason", "headers": ["PLAYER_ID", "SEASON_ID", "LEAGUE_ID", "TEAM_ID", "TEAM_ABBREVIATION", "PLAYER_AGE", "GP", "GS", "RANK_MIN", "RANK_FGM", "RANK_FGA", "RANK_FG_PCT", "RANK_FG3M", "RANK_FG3A", "RANK_FG3_PCT", "RANK_FTM", "RANK_FTA", "RANK_FT_PCT", "RANK_OREB", "RANK_DREB", "RANK_REB", "RANK_AST", "RANK_STL", "RANK_BLK", "RANK_TOV", "RANK_PTS", "RANK_EFF"], "rowSet": [[1628035, "2017-18", "00", 1610612761, "TOR", "NR", "NR", "NR", 481, 463, 482, null, 388, 406, null, 464, 470, null, 481, 483, 485, 499, 476, 440, 462, 469, 475], [1628035, "2018-19", "00", 1610612744, "GSW", "NR", "NR", "NR", 275, 282, 287, null, 239, 248, null, 341, 309, null, 91, 216, 176, 360, 321, 245, 333, 289, 276], [1628035, "2019-20", "00", 1610612739, "CLE", "NR", "NR", "NR", 321, 335, 337, null, 324, 303, null, 343, 339, null, 199, 318, 299, 412, 277, 305, 332, 347, 346], [1628035, "2020-21", "00", 1610612747, "LAL", "NR", "NR", "NR", 417, 383, 405, null, 330, 352, null, 422, 401, null, 288, 421, 403, 469, 421, 495, 461, 392, 402], [1628035, "2021-22", "00", 1610612741, "CHI", "NR", "NR", "NR", 446, 453, 446, null, 389, 393, null, 511, 470, null, 408, 467, 454, 496, 494, 432, 461, 460, 474]]}, {"name": "SeasonRankingsPostSeason", "headers": ["PLAYER_ID", "SEASON_ID", "LEAGUE_ID", "TEAM_ID", "TEAM_ABBREVIATION", "PLAYER_AGE", "GP", "GS", "RANK_MIN", "RANK_FGM", "RANK_FGA", "RANK_FG_PCT", "RANK_FG3M", "RANK_FG3A", "RANK_FG3_PCT", "RANK_FTM", "RANK_FTA", "RANK_FT_PCT", "RANK_OREB", "RANK_DREB", "RANK_REB", "RANK_AST", "RANK_STL", "RANK_BLK", "RANK_TOV", "RANK_PTS", "RANK_EFF"], "rowSet": [[1628035, "2018-19", "00", 1610612744, "GSW", "NR", "NR", "NR", 58, 80, 80, null, 61, 59, null, 125, 94, null, 29, 59, 53, 129, 122, 96, 98, 81, 81], [1628035, "2020-21", "00", 1610612747, "LAL", "NR", "NR", "NR", 201, 212, 208, null, 158, 156, null, 178, 183, null, 185, 198, 206, 195, 180, 156, 190, 219, 233]]}]}, {"resource": "commonplayerinfo", "parameters": [{"PlayerID": 1628035}, {"LeagueID": null}], "resultSets": [{"name": "CommonPlayerInfo", "headers": ["PERSON_ID", "FIRST_NAME", "LAST_NAME", "DISPLAY_FIRST_LAST", "DISPLAY_LAST_COMMA_FIRST", "DISPLAY_FI_LAST", "PLAYER_SLUG", "BIRTHDATE", "SCHOOL", "COUNTRY", "LAST_AFFILIATION", "HEIGHT", "WEIGHT", "SEASON_EXP", "JERSEY", "POSITION", "ROSTERSTATUS", "GAMES_PLAYED_CURRENT_SEASON_FLAG", "TEAM_ID", "TEAM_NAME", "TEAM_ABBREVIATION", "TEAM_CODE", "TEAM_CITY", "PLAYERCODE", "FROM_YEAR", "TO_YEAR", "DLEAGUE_FLAG", "NBA_FLAG", "GAMES_PLAYED_FLAG", "DRAFT_YEAR", "DRAFT_ROUND", "DRAFT_NUMBER", "GREATEST_75_FLAG"], "rowSet": [[1628035, "Alfonzo", "McKinnie", "Alfonzo McKinnie", "McKinnie, Alfonzo", "A. McKinnie", "alfonzo-mckinnie", "1992-09-17T00:00:00", "Wisc.-Green Bay", "USA", "Wisconsin-Green Bay/USA", "6-7", "215", 5, "", "Forward", "Inactive", "N", 0, "", "", "", "", "alfonzo_mckinnie", 2017, 2021, "Y", "Y", "Y", "Undrafted", "Undrafted", "Undrafted", "N"]]}, {"name": "PlayerHeadlineStats", "headers": ["PLAYER_ID", "PLAYER_NAME", "TimeFrame", "PTS", "AST", "REB", "ALL_STAR_APPEARANCES"], "rowSet": [[1628035, "Alfonzo McKinnie", "career", 4.0, 0.3, 2.5, 0]]}, {"name": "AvailableSeasons", "headers": ["SEASON_ID"], "rowSet": [["12017"], ["22017"], ["12018"], ["22018"], ["42018"], ["12019"], ["22019"], ["12020"], ["22020"], ["42020"], ["22021"]]}]}]