[{"resource": "playercareerstats", "parameters": {"PerMode": "Totals", "PlayerID": 193, "LeagueID": null}, "resultSets": [{"name": "SeasonTotalsRegularSeason", "headers": ["PLAYER_ID", "SEASON_ID", "LEAGUE_ID", "TEAM_ID", "TEAM_ABBREVIATION", "PLAYER_AGE", "GP", "GS", "MIN", "FGM", "FGA", "FG_PCT", "FG3M", "FG3A", "FG3_PCT", "FTM", "FTA", "FT_PCT", "OREB", "DREB", "REB", "AST", "STL", "BLK", "TOV", "PF", "PTS"], "rowSet": [[193, "1989-90", "00", 1610612751, "NJN", 23.0, 21, 0, 108.0, 14, 40, 0.35, 0, 0, 0.0, 9, 15, 0.6, 11, 23, 34, 7, 2, 2, 11, 20, 37], [193, "1990-91", "00", 1610612743, "DEN", 24.0, 3, 0, 21.0, 2, 4, 0.5, 0, 0, 0.0, 6, 8, 0.75, 3, 2, 5, 0, 1, 0, 0, 6, 10], [193, "1991-92", "00", 1610612752, "NYK", 25.0, 82, 0, 2198.0, 203, 399, 0.509, 0, 0, 0.0, 167, 260, 0.642, 216, 357, 573, 106, 46, 20, 101, 229, 573], [193, "1992-93", "00", 1610612752, "NYK", 26.0, 81, 0, 2482.0, 316, 629, 0.502, 0, 0, 0.0, 199, 292, 0.682, 231, 409, 640, 170, 43, 19, 137, 240, 831], [193, "1993-94", "00", 1610612752, "NYK", 27.0, 73, 12, 1903.0, 206, 433, 0.476, 0, 1, 0.0, 116, 161, 0.72, 158, 269, 427, 151, 31, 9, 107, 190, 528], [193, "1994-95", "00", 1610612752, "NYK", 28.0, 77, 11, 2496.0, 287, 507, 0.566, 0, 1, 0.0, 191, 298, 0.641, 182, 468, 650, 240, 69, 21, 123, 253, 765], [193, "1995-96", "00", 1610612752, "NYK", 29.0, 82, 82, 3457.0, 449, 798, 0.563, 0, 0, 0.0, 298, 414, 0.72, 220, 544, 764, 363, 69, 34, 211, 246, 1196], [193, "1996-97", "00", 1610612766, "CHH", 30.0, 73, 73, 3142.0, 433, 825, 0.525, 1, 3, 0.333, 319, 428, 0.745, 186, 643, 829, 414, 76, 33, 165, 202, 1186], [193, "1997-98", "00", 1610612766, "CHH", 31.0, 81, 80, 3148.0, 389, 764, 0.509, 0, 4, 0.0, 261, 402, 0.649, 177, 649, 826, 342, 68, 18, 146, 182, 1039], [193, "1999-00", "00", 1610612766, "CHH", 33.0, 82, 81, 3133.0, 317, 661, 0.48, 0, 1, 0.0, 314, 421, 0.746, 145, 554, 699, 367, 74, 29, 160, 220, 948], [193, "2000-01", "00", 1610612748, "MIA", 34.0, 80, 80, 3255.0, 460, 954, 0.482, 0, 0, 0.0, 370, 474, 0.781, 169, 601, 770, 248, 80, 25, 179, 231, 1290], [193, "2001-02", "00", 1610612749, "MIL", 35.0, 82, 82, 3140.0, 316, 626, 0.505, 1, 1, 1.0, 154, 221, 0.697, 124, 522, 646, 346, 57, 22, 130, 187, 787], [193, "2002-03", "00", 1610612749, "MIL", 36.0, 65, 58, 2118.0, 191, 393, 0.486, 0, 1, 0.0, 84, 117, 0.718, 90, 326, 416, 209, 32, 12, 79, 147, 466]]}, {"name": "CareerTotalsRegularSeason", "headers": ["PLAYER_ID", "LEAGUE_ID", "Team_ID", "GP", "GS", "MIN", "FGM", "FGA", "FG_PCT", "FG3M", "FG3A", "FG3_PCT", "FTM", "FTA", "FT_PCT", "OREB", "DREB", "REB", "AST", "STL", "BLK", "TOV", "PF", "PTS"], "rowSet": [[193, "00", 0, 882, 559, 30601.0, 3583, 7033, 0.509455, 2, 12, 0.166666, 2488, 3511, 0.70863, 1912, 5367, 7279, 2963, 648, 244, 1549, 2353, 9656]]}, {"name": "SeasonTotalsPostSeason", "headers": ["PLAYER_ID", "SEASON_ID", "LEAGUE_ID", "TEAM_ID", "TEAM_ABBREVIATION", "PLAYER_AGE", "GP", "GS", "MIN", "FGM", "FGA", "FG_PCT", "FG3M", "FG3A", "FG3_PCT", "FTM", "FTA", "FT_PCT", "OREB", "DREB", "REB", "AST", "STL", "BLK", "TOV", "PF", "PTS"], "rowSet": [[193, "1991-92", "00", 1610612752, "NYK", 25.0, 12, 0, 288.0, 19, 43, 0.442, 0, 0, 0.0, 22, 28, 0.786, 28, 48, 76, 10, 2, 8, 11, 34, 60], [193, "1992-93", "00", 1610612752, "NYK", 26.0, 15, 0, 510.0, 72, 122, 0.59, 0, 0, 0.0, 43, 68, 0.632, 55, 54, 109, 41, 10, 6, 23, 50, 187], [193, "1993-94", "00", 1610612752, "NYK", 27.0, 25, 0, 660.0, 67, 137, 0.489, 0, 0, 0.0, 55, 77, 0.714, 53, 93, 146, 46, 15, 5, 36, 66, 189], [193, "1994-95", "00", 1610612752, "NYK", 28.0, 11, 0, 352.0, 31, 51, 0.608, 0, 1, 0.0, 43, 69, 0.623, 23, 45, 68, 24, 6, 6, 26, 28, 105], [193, "1995-96", "00", 1610612752, "NYK", 29.0, 8, 8, 350.0, 41, 78, 0.526, 0, 0, 0.0, 19, 28, 0.679, 17, 45, 62, 26, 4, 1, 20, 20, 101], [193, "1996-97", "00", 1610612766, "CHH", 30.0, 3, 3, 131.0, 16, 38, 0.421, 0, 0, 0.0, 7, 13, 0.538, 8, 28, 36, 9, 1, 1, 9, 6, 39], [193, "1997-98", "00", 1610612766, "CHH", 31.0, 9, 9, 367.0, 57, 99, 0.576, 0, 1, 0.0, 25, 42, 0.595, 17, 54, 71, 31, 8, 0, 22, 17, 139], [193, "1999-00", "00", 1610612766, "CHH", 33.0, 4, 4, 179.0, 18, 38, 0.474, 0, 1, 0.0, 14, 20, 0.7, 16, 23, 39, 22, 4, 0, 13, 13, 50], [193, "2000-01", "00", 1610612748, "MIA", 34.0, 3, 3, 98.0, 5, 13, 0.385, 0, 1, 0.0, 6, 6, 1.0, 1, 8, 9, 4, 1, 0, 7, 6, 16], [193, "2002-03", "00", 1610612749, "MIL", 36.0, 6, 0, 157.0, 7, 17, 0.412, 0, 0, 0.0, 9, 13, 0.692, 4, 16, 20, 1, 3, 1, 8, 17, 23]]}, {"name": "CareerTotalsPostSeason", "headers": ["PLAYER_ID", "LEAGUE_ID", "Team_ID", "GP", "GS", "MIN", "FGM", "FGA", "FG_PCT", "FG3M", "FG3A", "FG3_PCT", "FTM", "FTA", "FT_PCT", "OREB", "DREB", "REB", "AST", "STL", "BLK", "TOV", "PF", "PTS"], "rowSet": [[193, "00", 0, 96, 27, 3092.0, 333, 636, 0.523584, 0, 4, 0.0, 243, 364, 0.667582, 222, 414, 636, 214, 54, 28, 175, 257, 909]]}, {"name": "SeasonTotalsAllStarSeason", "headers": ["PLAYER_ID", "SEASON_ID", "LEAGUE_ID", "TEAM_ID", "TEAM_ABBREVIATION", "PLAYER_AGE", "GP", "GS", "MIN", "FGM", "FGA", "FG_PCT", "FG3M", "FG3A", "FG3_PCT", "FTM", "FTA", "FT_PCT", "OREB", "DREB", "REB", "AST", "STL", "BLK", "TOV", "PF", "PTS"], "rowSet": [[193, "2000-01", "00", 1610616833, "EST", 34.0, 1, 1, 20.0, 0, 3, 0.0, 0, 0, 0.0, 0, 0, 0.0, 2, 2, 4, 1, 1, 0, 2, 2, 0]]}, {"name": "CareerTotalsAllStarSeason", "headers": ["PLAYER_ID", "LEAGUE_ID", "Team_ID", "GP", "GS", "MIN", "FGM", "FGA", "FG_PCT", "FG3M", "FG3A", "FG3_PCT", "FTM", "FTA", "FT_PCT", "OREB", "DREB", "REB", "AST", "STL", "BLK", "TOV", "PF", "PTS"], "rowSet": [[193, "00", 0, 1, 1, 20.0, 0, 3, 0.0, 0, 0, 0.0, 0, 0, 0.0, 2, 2, 4, 1, 1, 0, 2, 2, 0]]}, {"name": "SeasonTotalsCollegeSeason", "headers": ["PLAYER_ID", "SEASON_ID", "LEAGUE_ID", "ORGANIZATION_ID", "SCHOOL_NAME", "PLAYER_AGE", "GP", "GS", "MIN", "FGM", "FGA", "FG_PCT", "FG3M", "FG3A", "FG3_PCT", "FTM", "FTA", "FT_PCT", "OREB", "DREB", "REB", "AST", "STL", "BLK", "TOV", "PF", "PTS"], "rowSet": []}, {"name": "CareerTotalsCollegeSeason", "headers": ["PLAYER_ID", "LEAGUE_ID", "ORGANIZATION_ID", "GP", "GS", "MIN", "FGM", "FGA", "FG_PCT", "FG3M", "FG3A", "FG3_PCT", "FTM", "FTA", "FT_PCT", "OREB", "DREB", "REB", "AST", "STL", "BLK", "TOV", "PF", "PTS"], "rowSet": []}, {"name": "SeasonTotalsShowcaseSeason", "headers": ["PLAYER_ID", "SEASON_ID", "LEAGUE_ID", "TEAM_ID", "TEAM_ABBREVIATION", "PLAYER_AGE", "GP", "GS", "MIN", "FGM", "FGA", "FG_PCT", "FG3M", "FG3A", "FG3_PCT", "FTM", "FTA", "FT_PCT", "OREB", "DREB", "REB", "AST", "STL", "BLK", "TOV", "PF", "PTS"], "rowSet": []}, {"name": "CareerTotalsShowcaseSeason", "headers": ["PLAYER_ID", "LEAGUE_ID", "Team_ID", "GP", "GS", "MIN", "FGM", "FGA", "FG_PCT", "FG3M", "FG3A", "FG3_PCT", "FTM", "FTA", "FT_PCT", "OREB", "DREB", "REB", "AST", "STL", "BLK", "TOV", "PF", "PTS"], "rowSet": []}, {"name": "SeasonRankingsRegularSeason", "headers": ["PLAYER_ID", "SEASON_ID", "LEAGUE_ID", "TEAM_ID", "TEAM_ABBREVIATION", "PLAYER_AGE", "GP", "GS", "RANK_MIN", "RANK_FGM", "RANK_FGA", "RANK_FG_PCT", "RANK_FG3M", "RANK_FG3A", "RANK_FG3_PCT", "RANK_FTM", "RANK_FTA", "RANK_FT_PCT", "RANK_OREB", "RANK_DREB", "RANK_REB", "RANK_AST", "RANK_STL", "RANK_BLK", "RANK_TOV", "RANK_PTS", "RANK_EFF"], "rowSet": [[193, "1989-90", "00", 1610612751, "NJN", "NR", "NR", "NR", 341, 336, 334, null, 231, 322, null, 333, 333, null, 315, 316, 316, 334, 346, 303, 329, 339, 335], [193, "1990-91", "00", 1610612743, "DEN", "NR", "NR", "NR", 377, 378, 379, null, 235, 329, null, 355, 360, null, 355, 372, 370, 377, 355, 359, 381, 373, 369], [193, "1991-92", "00", 1610612752, "NYK", "NR", "NR", "NR", 102, 186, 196, null, 240, 326, null, 102, 86, 139, 33, 46, 40, 179, 170, 166, 148, 176, 122], [193, "1992-93", "00", 1610612752, "NYK", "NR", "NR", "NR", 67, 117, 127, 38, 244, 333, null, 79, 66, 128, 22, 31, 31, 110, 179, 158, 87, 112, 80], [193, "1993-94", "00", 1610612752, "NYK", "NR", "NR", "NR", 132, 177, 180, null, 247, 293, null, 145, 145, null, 54, 78, 68, 131, 226, 249, 130, 177, 148], [193, "1994-95", "00", 1610612752, "NYK", "NR", "NR", "NR", 64, 123, 149, null, 283, 316, null, 81, 58, 129, 36, 19, 25, 70, 95, 152, 105, 126, 43], [193, "1995-96", "00", 1610612752, "NYK", "NR", "NR", "NR", 1, 50, 82, 4, 301, 366, null, 31, 24, 115, 22, 12, 14, 29, 98, 114, 26, 52, 15], [193, "1996-97", "00", 1610612766, "CHH", "NR", "NR", "NR", 11, 53, 77, 15, 271, 301, null, 26, 26, 80, 40, 4, 5, 23, 88, 105, 63, 54, 6], [193, "1997-98", "00", 1610612766, "CHH", "NR", "NR", "NR", 11, 68, 82, 17, 274, 265, null, 42, 27, 133, 48, 4, 7, 28, 104, 175, 79, 70, 15], [193, "1999-00", "00", 1610612766, "CHH", "NR", "NR", "NR", 10, 100, 110, 29, 281, 323, null, 24, 19, 87, 62, 9, 15, 28, 95, 125, 67, 82, 22], [193, "2000-01", "00", 1610612748, "MIA", "NR", "NR", "NR", 4, 45, 52, 19, 295, 368, null, 15, 13, 65, 45, 9, 12, 68, 73, 146, 41, 43, 22], [193, "2001-02", "00", 1610612749, "MIL", "NR", "NR", "NR", 11, 99, 122, 13, 245, 326, null, 101, 90, 109, 82, 14, 23, 35, 136, 164, 89, 108, 41], [193, "2002-03", "00", 1610612749, "MIL", "NR", "NR", "NR", 109, 178, 198, null, 275, 317, null, 177, 176, null, 120, 58, 76, 79, 230, 242, 178, 191, 133]]}, {"name": "SeasonRankingsPostSeason", "headers": ["PLAYER_ID", "SEASON_ID", "LEAGUE_ID", "TEAM_ID", "TEAM_ABBREVIATION", "PLAYER_AGE", "GP", "GS", "RANK_MIN", "RANK_FGM", "RANK_FGA", "RANK_FG_PCT", "RANK_FG3M", "RANK_FG3A", "RANK_FG3_PCT", "RANK_FTM", "RANK_FTA", "RANK_FT_PCT", "RANK_OREB", "RANK_DREB", "RANK_REB", "RANK_AST", "RANK_STL", "RANK_BLK", "RANK_TOV", "RANK_PTS", "RANK_EFF"], "rowSet": [[193, "1991-92", "00", 1610612752, "NYK", "NR", "NR", "NR", 44, 84, 85, null, 77, 118, null, 45, 45, 42, 22, 23, 25, 78, 110, 29, 54, 76, 47], [193, "1992-93", "00", 1610612752, "NYK", "NR", "NR", "NR", 18, 20, 27, 3, 81, 114, null, 16, 13, 62, 5, 20, 15, 24, 36, 36, 27, 21, 15], [193, "1993-94", "00", 1610612752, "NYK", "NR", "NR", "NR", 11, 21, 26, null, 81, 114, null, 11, 9, 64, 7, 10, 7, 21, 23, 42, 15, 21, 13], [193, "1994-95", "00", 1610612752, "NYK", "NR", "NR", "NR", 37, 50, 65, null, 101, 109, null, 21, 17, 73, 20, 28, 23, 41, 54, 30, 21, 40, 37], [193, "1995-96", "00", 1610612752, "NYK", "NR", "NR", "NR", 29, 35, 41, 9, 100, 121, null, 39, 37, 52, 27, 22, 27, 37, 66, 80, 27, 43, 35], [193, "1996-97", "00", 1610612766, "CHH", "NR", "NR", "NR", 84, 89, 84, 53, 102, 129, null, 90, 80, 79, 65, 45, 50, 80, 122, 94, 69, 93, 88], [193, "1997-98", "00", 1610612766, "CHH", "NR", "NR", "NR", 29, 20, 32, 3, 90, 101, null, 32, 23, 71, 30, 20, 22, 31, 40, 123, 23, 30, 27], [193, "1999-00", "00", 1610612766, "CHH", "NR", "NR", "NR", 63, 78, 87, 15, 98, 107, null, 61, 58, 63, 33, 63, 58, 43, 76, 120, 50, 81, 68], [193, "2000-01", "00", 1610612748, "MIA", "NR", "NR", "NR", 106, 131, 131, null, 97, 104, null, 93, 105, 1, 140, 114, 127, 105, 121, 130, 77, 125, 137], [193, "2002-03", "00", 1610612749, "MIL", "NR", "NR", "NR", 100, 141, 143, null, 101, 131, null, 94, 93, null, 117, 98, 110, 158, 103, 96, 92, 130, 134]]}]}, {"resource": "commonplayerinfo", "parameters": [{"PlayerID": 193}, {"LeagueID": null}], "resultSets": [{"name": "CommonPlayerInfo", "headers": ["PERSON_ID", "FIRST_NAME", "LAST_NAME", "DISPLAY_FIRST_LAST", "DISPLAY_LAST_COMMA_FIRST", "DISPLAY_FI_LAST", "PLAYER_SLUG", "BIRTHDATE", "SCHOOL", "COUNTRY", "LAST_AFFILIATION", "HEIGHT", "WEIGHT", "SEASON_EXP", "JERSEY", "POSITION", "ROSTERSTATUS", "GAMES_PLAYED_CURRENT_SEASON_FLAG", "TEAM_ID", "TEAM_NAME", "TEAM_ABBREVIATION", "TEAM_CODE", "TEAM_CITY", "PLAYERCODE", "FROM_YEAR", "TO_YEAR", "DLEAGUE_FLAG", "NBA_FLAG", "GAMES_PLAYED_FLAG", "DRAFT_YEAR", "DRAFT_ROUND", "DRAFT_NUMBER", "GREATEST_75_FLAG"], "rowSet": [[193, "Anthony", "Mason", "Anthony Mason", "Mason, Anthony", "A. Mason", "anthony-mason", "1966-12-14T00:00:00", "Tennessee State", "USA", "Tennessee State/USA", "6-8", "255", 14, "17", "Forward", "Inactive", "N", 1610612752, "Knicks", "NYK", "knicks", "New York", "anthony_mason", 1989, 2002, "N", "Y", "Y", "1988", "3", "53", "N"]]}, {"name": "PlayerHeadlineStats", "headers": ["PLAYER_ID", "PLAYER_NAME", "TimeFrame", "PTS", "AST", "REB", "ALL_STAR_APPEARANCES"], "rowSet": [[193, "Anthony Mason", "career", 10.9, 3.4, 8.3, 1]]}, {"name": "AvailableSeasons", "headers": ["SEASON_ID"], "rowSet": [["21989"], ["21990"], ["21991"], ["41991"], ["21992"], ["41992"], ["21993"], ["41993"], ["21994"], ["41994"], ["21995"], ["41995"], ["21996"], ["41996"], ["11997"], ["21997"], ["41997"], ["11998"], ["11999"], ["21999"], ["41999"], ["12000"], ["22000"], ["32000"], ["42000"], ["22001"], ["12002"], ["22002"], ["42002"]]}]}]