[{"resource": "playercareerstats", "parameters": {"PerMode": "Totals", "PlayerID": 202702, "LeagueID": null}, "resultSets": [{"name": "SeasonTotalsRegularSeason", "headers": ["PLAYER_ID", "SEASON_ID", "LEAGUE_ID", "TEAM_ID", "TEAM_ABBREVIATION", "PLAYER_AGE", "GP", "GS", "MIN", "FGM", "FGA", "FG_PCT", "FG3M", "FG3A", "FG3_PCT", "FTM", "FTA", "FT_PCT", "OREB", "DREB", "REB", "AST", "STL", "BLK", "TOV", "PF", "PTS"], "rowSet": [[202702, "2011-12", "00", 1610612743, "DEN", 22.0, 46, 39, 1037.0, 181, 309, 0.586, 0, 0, 0.0, 109, 164, 0.665, 142, 210, 352, 36, 34, 47, 54, 116, 471], [202702, "2012-13", "00", 1610612743, "DEN", 23.0, 80, 80, 2248.0, 380, 689, 0.552, 0, 0, 0.0, 163, 266, 0.613, 260, 474, 734, 77, 81, 83, 113, 234, 923], [202702, "2013-14", "00", 1610612743, "DEN", 24.0, 80, 77, 2178.0, 447, 820, 0.545, 0, 3, 0.0, 202, 311, 0.65, 238, 446, 684, 96, 70, 69, 135, 193, 1096], [202702, "2014-15", "00", 1610612743, "DEN", 25.0, 75, 71, 2086.0, 373, 736, 0.507, 1, 8, 0.125, 199, 288, 0.691, 242, 426, 668, 89, 62, 57, 118, 211, 946], [202702, "2015-16", "00", 1610612743, "DEN", 26.0, 67, 64, 1694.0, 349, 626, 0.558, 1, 2, 0.5, 136, 222, 0.613, 235, 346, 581, 79, 32, 60, 91, 169, 835], [202702, "2016-17", "00", 1610612743, "DEN", 27.0, 61, 34, 1296.0, 228, 416, 0.548, 0, 6, 0.0, 131, 189, 0.693, 183, 279, 462, 55, 43, 40, 59, 124, 587], [202702, "2017-18", "00", 1610612743, "DEN", 28.0, 32, 7, 461.0, 76, 148, 0.514, 0, 1, 0.0, 36, 51, 0.706, 68, 85, 153, 18, 12, 13, 23, 51, 188], [202702, "2018-19", "00", 1610612751, "BKN", 29.0, 12, 0, 118.0, 25, 42, 0.595, 1, 5, 0.2, 10, 16, 0.625, 15, 29, 44, 2, 2, 4, 6, 8, 61], [202702, "2018-19", "00", 1610612745, "HOU", 29.0, 25, 13, 610.0, 131, 223, 0.587, 7, 20, 0.35, 54, 83, 0.651, 82, 124, 206, 18, 15, 19, 27, 74, 323], [202702, "2018-19", "00", 0, "TOT", 29.0, 37, 13, 728.0, 156, 265, 0.589, 8, 25, 0.32, 64, 99, 0.646, 97, 153, 250, 20, 17, 23, 33, 82, 384]]}, {"name": "CareerTotalsRegularSeason", "headers": ["PLAYER_ID", "LEAGUE_ID", "Team_ID", "GP", "GS", "MIN", "FGM", "FGA", "FG_PCT", "FG3M", "FG3A", "FG3_PCT", "FTM", "FTA", "FT_PCT", "OREB", "DREB", "REB", "AST", "STL", "BLK", "TOV", "PF", "PTS"], "rowSet": [[202702, "00", 0, 478, 385, 11728.0, 2190, 4009, 0.54627, 10, 45, 0.222222, 1040, 1590, 0.654088, 1465, 2419, 3884, 470, 351, 392, 626, 1180, 5430]]}, {"name": "SeasonTotalsPostSeason", "headers": ["PLAYER_ID", "SEASON_ID", "LEAGUE_ID", "TEAM_ID", "TEAM_ABBREVIATION", "PLAYER_AGE", "GP", "GS", "MIN", "FGM", "FGA", "FG_PCT", "FG3M", "FG3A", "FG3_PCT", "FTM", "FTA", "FT_PCT", "OREB", "DREB", "REB", "AST", "STL", "BLK", "TOV", "PF", "PTS"], "rowSet": [[202702, "2011-12", "00", 1610612743, "DEN", 22.0, 7, 7, 192.0, 32, 60, 0.533, 0, 0, 0.0, 9, 12, 0.75, 25, 45, 70, 4, 5, 8, 14, 20, 73], [202702, "2012-13", "00", 1610612743, "DEN", 23.0, 5, 4, 145.0, 20, 32, 0.625, 0, 0, 0.0, 11, 15, 0.733, 12, 30, 42, 1, 5, 1, 5, 22, 51], [202702, "2018-19", "00", 1610612745, "HOU", 29.0, 6, 0, 56.0, 9, 13, 0.692, 1, 1, 1.0, 5, 6, 0.833, 3, 18, 21, 2, 2, 0, 0, 6, 24]]}, {"name": "CareerTotalsPostSeason", "headers": ["PLAYER_ID", "LEAGUE_ID", "Team_ID", "GP", "GS", "MIN", "FGM", "FGA", "FG_PCT", "FG3M", "FG3A", "FG3_PCT", "FTM", "FTA", "FT_PCT", "OREB", "DREB", "REB", "AST", "STL", "BLK", "TOV", "PF", "PTS"], "rowSet": [[202702, "00", 0, 18, 11, 393.0, 61, 105, 0.580952, 1, 1, 1.0, 25, 33, 0.757575, 40, 93, 133, 7, 12, 9, 19, 48, 148]]}, {"name": "SeasonTotalsAllStarSeason", "headers": ["PLAYER_ID", "SEASON_ID", "LEAGUE_ID", "TEAM_ID", "TEAM_ABBREVIATION", "PLAYER_AGE", "GP", "GS", "MIN", "FGM", "FGA", "FG_PCT", "FG3M", "FG3A", "FG3_PCT", "FTM", "FTA", "FT_PCT", "OREB", "DREB", "REB", "AST", "STL", "BLK", "TOV", "PF", "PTS"], "rowSet": []}, {"name": "CareerTotalsAllStarSeason", "headers": ["PLAYER_ID", "LEAGUE_ID", "Team_ID", "GP", "GS", "MIN", "FGM", "FGA", "FG_PCT", "FG3M", "FG3A", "FG3_PCT", "FTM", "FTA", "FT_PCT", "OREB", "DREB", "REB", "AST", "STL", "BLK", "TOV", "PF", "PTS"], "rowSet": []}, {"name": "SeasonTotalsCollegeSeason", "headers": ["PLAYER_ID", "SEASON_ID", "LEAGUE_ID", "ORGANIZATION_ID", "SCHOOL_NAME", "PLAYER_AGE", "GP", "GS", "MIN", "FGM", "FGA", "FG_PCT", "FG3M", "FG3A", "FG3_PCT", "FTM", "FTA", "FT_PCT", "OREB", "DREB", "REB", "AST", "STL", "BLK", "TOV", "PF", "PTS"], "rowSet": [[202702, "2010-11", "00", 2857, "Morehead State", 21.0, 35, 34, 1216, 233, 374, 0.623, 0, 0, null, 139, 241, 0.577, 200, 308, 508, 37, 67, 82, 92, 108, 605], [202702, "2009-10", "00", 2857, "Morehead State", 20.0, 35, 32, 1060, 224, 397, 0.564, 1, 4, 0.25, 141, 237, 0.595, 148, 308, 456, 19, 56, 67, 84, 115, 590], [202702, "2008-09", "00", 2857, "Morehead State", 19.0, 36, 36, 1083, 194, 349, 0.556, 2, 5, 0.4, 109, 189, 0.577, 153, 315, 468, 52, 68, 68, 80, 103, 499], [202702, "2007-08", "00", 2857, "Morehead State", 18.0, 30, 20, 605, 132, 256, 0.516, 0, 3, 0.0, 51, 88, 0.58, 101, 140, 241, 9, 37, 24, 48, 90, 315]]}, {"name": "CareerTotalsCollegeSeason", "headers": ["PLAYER_ID", "LEAGUE_ID", "ORGANIZATION_ID", "GP", "GS", "MIN", "FGM", "FGA", "FG_PCT", "FG3M", "FG3A", "FG3_PCT", "FTM", "FTA", "FT_PCT", "OREB", "DREB", "REB", "AST", "STL", "BLK", "TOV", "PF", "PTS"], "rowSet": [[202702, "00", 0, 136, 122, 3964, 783, 1376, 0.569, 3, 12, 0.25, 440, 755, 0.583, 602, 1071, 1673, 117, 228, 241, 304, 416, 2009]]}, {"name": "SeasonTotalsShowcaseSeason", "headers": ["PLAYER_ID", "SEASON_ID", "LEAGUE_ID", "TEAM_ID", "TEAM_ABBREVIATION", "PLAYER_AGE", "GP", "GS", "MIN", "FGM", "FGA", "FG_PCT", "FG3M", "FG3A", "FG3_PCT", "FTM", "FTA", "FT_PCT", "OREB", "DREB", "REB", "AST", "STL", "BLK", "TOV", "PF", "PTS"], "rowSet": []}, {"name": "CareerTotalsShowcaseSeason", "headers": ["PLAYER_ID", "LEAGUE_ID", "Team_ID", "GP", "GS", "MIN", "FGM", "FGA", "FG_PCT", "FG3M", "FG3A", "FG3_PCT", "FTM", "FTA", "FT_PCT", "OREB", "DREB", "REB", "AST", "STL", "BLK", "TOV", "PF", "PTS"], "rowSet": []}, {"name": "SeasonRankingsRegularSeason", "headers": ["PLAYER_ID", "SEASON_ID", "LEAGUE_ID", "TEAM_ID", "TEAM_ABBREVIATION", "PLAYER_AGE", "GP", "GS", "RANK_MIN", "RANK_FGM", "RANK_FGA", "RANK_FG_PCT", "RANK_FG3M", "RANK_FG3A", "RANK_FG3_PCT", "RANK_FTM", "RANK_FTA", "RANK_FT_PCT", "RANK_OREB", "RANK_DREB", "RANK_REB", "RANK_AST", "RANK_STL", "RANK_BLK", "RANK_TOV", "RANK_PTS", "RANK_EFF"], "rowSet": [[202702, "2011-12", "00", 1610612743, "DEN", "NR", "NR", "NR", 219, 171, 217, null, 341, 401, null, 106, 94, 107, 32, 82, 59, 277, 195, 57, 213, 175, 115], [202702, "2012-13", "00", 1610612743, "DEN", "NR", "NR", "NR", 81, 71, 106, 9, 333, 406, null, 88, 60, 116, 8, 21, 13, 210, 60, 32, 107, 88, 41], [202702, "2013-14", "00", 1610612743, "DEN", "NR", "NR", "NR", 97, 47, 78, 9, 349, 352, null, 65, 49, 116, 9, 31, 18, 181, 81, 39, 73, 60, 36], [202702, "2014-15", "00", 1610612743, "DEN", "NR", "NR", "NR", 93, 68, 97, 15, 356, 352, null, 52, 42, 112, 8, 23, 18, 203, 102, 54, 83, 80, 46], [202702, "2015-16", "00", 1610612743, "DEN", "NR", "NR", "NR", 157, 92, 127, 7, 355, 386, null, 107, 80, 116, 9, 62, 32, 228, 241, 52, 142, 113, 66], [202702, "2016-17", "00", 1610612743, "DEN", "NR", "NR", "NR", 224, 172, 215, null, 401, 381, null, 106, 96, 101, 15, 91, 58, 284, 185, 83, 221, 174, 123], [202702, "2017-18", "00", 1610612743, "DEN", "NR", "NR", "NR", 360, 338, 353, null, 445, 470, null, 303, 295, null, 118, 318, 268, 391, 364, 260, 355, 343, 328], [202702, "2018-19", "00", 1610612745, "HOU", "NR", "NR", "NR", 325, 266, 294, null, 368, 374, null, 221, 198, null, 71, 239, 174, 396, 330, 182, 318, 277, 250]]}, {"name": "SeasonRankingsPostSeason", "headers": ["PLAYER_ID", "SEASON_ID", "LEAGUE_ID", "TEAM_ID", "TEAM_ABBREVIATION", "PLAYER_AGE", "GP", "GS", "RANK_MIN", "RANK_FGM", "RANK_FGA", "RANK_FG_PCT", "RANK_FG3M", "RANK_FG3A", "RANK_FG3_PCT", "RANK_FTM", "RANK_FTA", "RANK_FT_PCT", "RANK_OREB", "RANK_DREB", "RANK_REB", "RANK_AST", "RANK_STL", "RANK_BLK", "RANK_TOV", "RANK_PTS", "RANK_EFF"], "rowSet": [[202702, "2011-12", "00", 1610612743, "DEN", "NR", "NR", "NR", 78, 65, 79, 2, 113, 137, null, 85, 89, null, 18, 34, 31, 115, 70, 31, 51, 73, 46], [202702, "2012-13", "00", 1610612743, "DEN", "NR", "NR", "NR", 101, 98, 113, null, 112, 148, null, 77, 78, 45, 44, 61, 55, 153, 75, 108, 113, 97, 78], [202702, "2018-19", "00", 1610612745, "HOU", "NR", "NR", "NR", 149, 135, 155, null, 130, 165, null, 117, 125, null, 112, 99, 101, 158, 122, 141, 180, 136, 117]]}]}, {"resource": "commonplayerinfo", "parameters": [{"PlayerID": 202702}, {"LeagueID": null}], "resultSets": [{"name": "CommonPlayerInfo", "headers": ["PERSON_ID", "FIRST_NAME", "LAST_NAME", "DISPLAY_FIRST_LAST", "DISPLAY_LAST_COMMA_FIRST", "DISPLAY_FI_LAST", "PLAYER_SLUG", "BIRTHDATE", "SCHOOL", "COUNTRY", "LAST_AFFILIATION", "HEIGHT", "WEIGHT", "SEASON_EXP", "JERSEY", "POSITION", "ROSTERSTATUS", "GAMES_PLAYED_CURRENT_SEASON_FLAG", "TEAM_ID", "TEAM_NAME", "TEAM_ABBREVIATION", "TEAM_CODE", "TEAM_CITY", "PLAYERCODE", "FROM_YEAR", "TO_YEAR", "DLEAGUE_FLAG", "NBA_FLAG", "GAMES_PLAYED_FLAG", "DRAFT_YEAR", "DRAFT_ROUND", "DRAFT_NUMBER", "GREATEST_75_FLAG"], "rowSet": [[202702, "Kenneth", "Faried", "Kenneth Faried", "Faried, Kenneth", "K. Faried", "kenneth-faried", "1989-11-19T00:00:00", "Morehead State", "USA", "Morehead State/USA", "6-8", "220", 9, "35", "Forward-Center", "Inactive", "N", 1610612743, "Nuggets", "DEN", "nuggets", "Denver", "kenneth_faried", 2011, 2018, "Y", "Y", "Y", "2011", "1", "22", "N"]]}, {"name": "PlayerHeadlineStats", "headers": ["PLAYER_ID", "PLAYER_NAME", "TimeFrame", "PTS", "AST", "REB", "ALL_STAR_APPEARANCES"], "rowSet": [[202702, "Kenneth Faried", "career", 11.4, 1.0, 8.1, 0]]}, {"name": "AvailableSeasons", "headers": ["SEASON_ID"], "rowSet": [["12011"], ["22011"], ["42011"], ["12012"], ["22012"], ["42012"], ["12013"], ["22013"], ["12014"], ["22014"], ["12015"], ["22015"], ["12016"], ["22016"], ["12017"], ["22017"], ["12018"], ["22018"], ["42018"]]}]}]