[{"resource": "playercareerstats", "parameters": {"PerMode": "Totals", "PlayerID": 2584, "LeagueID": null}, "resultSets": [{"name": "SeasonTotalsRegularSeason", "headers": ["PLAYER_ID", "SEASON_ID", "LEAGUE_ID", "TEAM_ID", "TEAM_ABBREVIATION", "PLAYER_AGE", "GP", "GS", "MIN", "FGM", "FGA", "FG_PCT", "FG3M", "FG3A", "FG3_PCT", "FTM", "FTA", "FT_PCT", "OREB", "DREB", "REB", "AST", "STL", "BLK", "TOV", "PF", "PTS"], "rowSet": [[2584, "2003-04", "00", 1610612755, "PHI", 22.0, 53, 0, 767.0, 143, 357, 0.401, 19, 61, 0.311, 59, 81, 0.728, 16, 49, 65, 53, 26, 5, 59, 83, 364], [2584, "2004-05", "00", 1610612755, "PHI", 23.0, 57, 21, 1067.0, 155, 423, 0.366, 30, 105, 0.286, 97, 125, 0.776, 22, 111, 133, 100, 34, 6, 75, 121, 437], [2584, "2005-06", "00", 1610612755, "PHI", 24.0, 10, 2, 153.0, 28, 66, 0.424, 10, 19, 0.526, 4, 5, 0.8, 1, 14, 15, 5, 2, 0, 12, 13, 70], [2584, "2006-07", "00", 1610612755, "PHI", 25.0, 74, 36, 1842.0, 357, 868, 0.411, 51, 157, 0.325, 74, 111, 0.667, 42, 116, 158, 112, 56, 4, 106, 144, 839], [2584, "2007-08", "00", 1610612755, "PHI", 26.0, 74, 74, 1970.0, 379, 870, 0.436, 51, 179, 0.285, 112, 148, 0.757, 32, 150, 182, 151, 54, 22, 109, 119, 921], [2584, "2008-09", "00", 1610612755, "PHI", 27.0, 81, 60, 1828.0, 286, 658, 0.435, 51, 161, 0.317, 62, 85, 0.729, 29, 97, 126, 158, 53, 13, 64, 154, 685], [2584, "2009-10", "00", 1610612755, "PHI", 28.0, 73, 18, 1553.0, 248, 543, 0.457, 47, 136, 0.346, 95, 114, 0.833, 20, 109, 129, 152, 32, 11, 67, 135, 638], [2584, "2010-11", "00", 1610612740, "NOH", 29.0, 77, 13, 1674.0, 270, 609, 0.443, 54, 155, 0.348, 78, 100, 0.78, 22, 139, 161, 74, 36, 13, 67, 143, 672], [2584, "2011-12", "00", 1610612737, "ATL", 30.0, 53, 2, 922.0, 153, 325, 0.471, 50, 113, 0.442, 48, 56, 0.857, 15, 65, 80, 40, 23, 6, 33, 74, 404], [2584, "2012-13", "00", 1610612746, "LAC", 31.0, 72, 60, 1188.0, 178, 386, 0.461, 71, 166, 0.428, 23, 32, 0.719, 17, 80, 97, 55, 29, 12, 31, 96, 450], [2584, "2013-14", "00", 1610612746, "LAC", 32.0, 55, 9, 869.0, 102, 271, 0.376, 41, 121, 0.339, 28, 34, 0.824, 12, 66, 78, 50, 22, 11, 34, 96, 273], [2584, "2014-15", "00", 1610612753, "ORL", 33.0, 52, 2, 951.0, 118, 306, 0.386, 42, 121, 0.347, 28, 34, 0.824, 14, 65, 79, 68, 26, 5, 48, 81, 306]]}, {"name": "CareerTotalsRegularSeason", "headers": ["PLAYER_ID", "LEAGUE_ID", "Team_ID", "GP", "GS", "MIN", "FGM", "FGA", "FG_PCT", "FG3M", "FG3A", "FG3_PCT", "FTM", "FTA", "FT_PCT", "OREB", "DREB", "REB", "AST", "STL", "BLK", "TOV", "PF", "PTS"], "rowSet": [[2584, "00", 0, 731, 297, 14785.0, 2417, 5682, 0.425378, 517, 1494, 0.34605, 708, 925, 0.765405, 242, 1061, 1303, 1018, 393, 108, 705, 1259, 6059]]}, {"name": "SeasonTotalsPostSeason", "headers": ["PLAYER_ID", "SEASON_ID", "LEAGUE_ID", "TEAM_ID", "TEAM_ABBREVIATION", "PLAYER_AGE", "GP", "GS", "MIN", "FGM", "FGA", "FG_PCT", "FG3M", "FG3A", "FG3_PCT", "FTM", "FTA", "FT_PCT", "OREB", "DREB", "REB", "AST", "STL", "BLK", "TOV", "PF", "PTS"], "rowSet": [[2584, "2004-05", "00", 1610612755, "PHI", 23.0, 5, 0, 64.0, 8, 18, 0.444, 2, 9, 0.222, 9, 10, 0.9, 3, 6, 9, 3, 1, 0, 2, 5, 27], [2584, "2007-08", "00", 1610612755, "PHI", 26.0, 6, 6, 142.0, 22, 51, 0.431, 1, 5, 0.2, 9, 14, 0.643, 2, 6, 8, 12, 5, 4, 9, 19, 54], [2584, "2008-09", "00", 1610612755, "PHI", 27.0, 6, 6, 148.0, 21, 51, 0.412, 4, 11, 0.364, 1, 3, 0.333, 0, 6, 6, 7, 0, 1, 5, 13, 47], [2584, "2010-11", "00", 1610612740, "NOH", 29.0, 6, 0, 84.0, 14, 36, 0.389, 2, 9, 0.222, 4, 7, 0.571, 1, 4, 5, 4, 2, 0, 3, 14, 34], [2584, "2011-12", "00", 1610612737, "ATL", 30.0, 5, 0, 63.0, 6, 13, 0.462, 1, 4, 0.25, 0, 0, 0.0, 1, 7, 8, 3, 0, 0, 2, 6, 13], [2584, "2012-13", "00", 1610612746, "LAC", 31.0, 3, 0, 20.0, 2, 3, 0.667, 0, 1, 0.0, 2, 2, 1.0, 0, 3, 3, 2, 1, 0, 0, 0, 6], [2584, "2013-14", "00", 1610612746, "LAC", 32.0, 5, 0, 19.0, 1, 5, 0.2, 1, 4, 0.25, 2, 2, 1.0, 0, 7, 7, 1, 3, 0, 1, 3, 5]]}, {"name": "CareerTotalsPostSeason", "headers": ["PLAYER_ID", "LEAGUE_ID", "Team_ID", "GP", "GS", "MIN", "FGM", "FGA", "FG_PCT", "FG3M", "FG3A", "FG3_PCT", "FTM", "FTA", "FT_PCT", "OREB", "DREB", "REB", "AST", "STL", "BLK", "TOV", "PF", "PTS"], "rowSet": [[2584, "00", 0, 36, 12, 538.0, 74, 177, 0.418079, 11, 43, 0.255813, 27, 38, 0.710526, 7, 39, 46, 32, 12, 5, 22, 60, 186]]}, {"name": "SeasonTotalsAllStarSeason", "headers": ["PLAYER_ID", "SEASON_ID", "LEAGUE_ID", "TEAM_ID", "TEAM_ABBREVIATION", "PLAYER_AGE", "GP", "GS", "MIN", "FGM", "FGA", "FG_PCT", "FG3M", "FG3A", "FG3_PCT", "FTM", "FTA", "FT_PCT", "OREB", "DREB", "REB", "AST", "STL", "BLK", "TOV", "PF", "PTS"], "rowSet": []}, {"name": "CareerTotalsAllStarSeason", "headers": ["PLAYER_ID", "LEAGUE_ID", "Team_ID", "GP", "GS", "MIN", "FGM", "FGA", "FG_PCT", "FG3M", "FG3A", "FG3_PCT", "FTM", "FTA", "FT_PCT", "OREB", "DREB", "REB", "AST", "STL", "BLK", "TOV", "PF", "PTS"], "rowSet": []}, {"name": "SeasonTotalsCollegeSeason", "headers": ["PLAYER_ID", "SEASON_ID", "LEAGUE_ID", "ORGANIZATION_ID", "SCHOOL_NAME", "PLAYER_AGE", "GP", "GS", "MIN", "FGM", "FGA", "FG_PCT", "FG3M", "FG3A", "FG3_PCT", "FTM", "FTA", "FT_PCT", "OREB", "DREB", "REB", "AST", "STL", "BLK", "TOV", "PF", "PTS"], "rowSet": [[2584, "2002-03", "00", 2985, "Detroit Mercy", 21.0, 30, 30, 1021, 244, 498, 0.49, 37, 99, 0.374, 153, 190, 0.805, 32, 116, 148, 74, 40, 13, 68, 71, 678], [2584, "2001-02", "00", 2985, "Detroit Mercy", 20.0, 29, 27, 888, 147, 341, 0.431, 25, 88, 0.284, 77, 115, 0.67, 29, 93, 122, 55, 23, 9, 63, 75, 396], [2584, "2000-01", "00", 2985, "Detroit Mercy", 19.0, 33, 30, 1012, 167, 352, 0.474, 32, 86, 0.372, 70, 97, 0.722, 44, 122, 166, 80, 32, 3, 66, 82, 436], [2584, "1999-00", "00", 2985, "Detroit Mercy", 18.0, 32, 21, 800, 91, 218, 0.417, 26, 68, 0.382, 61, 75, 0.813, 24, 59, 83, 60, 22, 10, 49, 62, 269]]}, {"name": "CareerTotalsCollegeSeason", "headers": ["PLAYER_ID", "LEAGUE_ID", "ORGANIZATION_ID", "GP", "GS", "MIN", "FGM", "FGA", "FG_PCT", "FG3M", "FG3A", "FG3_PCT", "FTM", "FTA", "FT_PCT", "OREB", "DREB", "REB", "AST", "STL", "BLK", "TOV", "PF", "PTS"], "rowSet": [[2584, "00", 0, 124, 108, 3721, 649, 1409, 0.461, 120, 341, 0.352, 361, 477, 0.757, 129, 390, 519, 269, 117, 35, 246, 290, 1779]]}, {"name": "SeasonTotalsShowcaseSeason", "headers": ["PLAYER_ID", "SEASON_ID", "LEAGUE_ID", "TEAM_ID", "TEAM_ABBREVIATION", "PLAYER_AGE", "GP", "GS", "MIN", "FGM", "FGA", "FG_PCT", "FG3M", "FG3A", "FG3_PCT", "FTM", "FTA", "FT_PCT", "OREB", "DREB", "REB", "AST", "STL", "BLK", "TOV", "PF", "PTS"], "rowSet": []}, {"name": "CareerTotalsShowcaseSeason", "headers": ["PLAYER_ID", "LEAGUE_ID", "Team_ID", "GP", "GS", "MIN", "FGM", "FGA", "FG_PCT", "FG3M", "FG3A", "FG3_PCT", "FTM", "FTA", "FT_PCT", "OREB", "DREB", "REB", "AST", "STL", "BLK", "TOV", "PF", "PTS"], "rowSet": []}, {"name": "SeasonRankingsRegularSeason", "headers": ["PLAYER_ID", "SEASON_ID", "LEAGUE_ID", "TEAM_ID", "TEAM_ABBREVIATION", "PLAYER_AGE", "GP", "GS", "RANK_MIN", "RANK_FGM", "RANK_FGA", "RANK_FG_PCT", "RANK_FG3M", "RANK_FG3A", "RANK_FG3_PCT", "RANK_FTM", "RANK_FTA", "RANK_FT_PCT", "RANK_OREB", "RANK_DREB", "RANK_REB", "RANK_AST", "RANK_STL", "RANK_BLK", "RANK_TOV", "RANK_PTS", "RANK_EFF"], "rowSet": [[2584, "2003-04", "00", 1610612755, "PHI", "NR", "NR", "NR", 274, 220, 207, null, 154, 156, null, 233, 231, null, 325, 326, 333, 247, 249, 313, 222, 221, 304], [2584, "2004-05", "00", 1610612755, "PHI", "NR", "NR", "NR", 255, 231, 192, null, 150, 136, null, 180, 189, null, 311, 260, 272, 175, 219, 304, 193, 213, 276], [2584, "2005-06", "00", 1610612755, "PHI", "NR", "NR", "NR", 399, 369, 372, null, 198, 227, null, 416, 422, null, 432, 408, 417, 405, 417, 415, 379, 374, 406], [2584, "2006-07", "00", 1610612755, "PHI", "NR", "NR", "NR", 148, 82, 69, 110, 121, 109, null, 217, 211, null, 219, 248, 248, 155, 121, 322, 139, 108, 227], [2584, "2007-08", "00", 1610612755, "PHI", "NR", "NR", "NR", 130, 77, 72, 97, 125, 109, null, 152, 152, null, 247, 204, 223, 121, 139, 154, 112, 89, 171], [2584, "2008-09", "00", 1610612755, "PHI", "NR", "NR", "NR", 158, 131, 125, null, 134, 127, null, 224, 223, null, 265, 272, 277, 105, 128, 228, 213, 156, 203], [2584, "2009-10", "00", 1610612755, "PHI", "NR", "NR", "NR", 192, 160, 161, null, 141, 142, null, 180, 196, null, 307, 250, 268, 124, 222, 251, 205, 168, 210], [2584, "2010-11", "00", 1610612740, "NOH", "NR", "NR", "NR", 168, 140, 136, null, 134, 127, null, 198, 208, null, 305, 221, 246, 211, 200, 247, 199, 154, 217], [2584, "2011-12", "00", 1610612737, "ATL", "NR", "NR", "NR", 242, 199, 211, null, 109, 136, 7, 227, 249, null, 324, 308, 313, 264, 253, 301, 291, 199, 250], [2584, "2012-13", "00", 1610612746, "LAC", "NR", "NR", "NR", 235, 213, 219, null, 98, 122, 9, 321, 334, null, 332, 303, 319, 257, 255, 253, 317, 220, 255], [2584, "2013-14", "00", 1610612746, "LAC", "NR", "NR", "NR", 287, 283, 270, null, 170, 173, null, 311, 327, null, 361, 332, 344, 275, 292, 263, 309, 284, 325], [2584, "2014-15", "00", 1610612753, "ORL", "NR", "NR", "NR", 285, 291, 273, null, 181, 185, null, 337, 351, null, 359, 349, 355, 248, 283, 353, 271, 292, 340]]}, {"name": "SeasonRankingsPostSeason", "headers": ["PLAYER_ID", "SEASON_ID", "LEAGUE_ID", "TEAM_ID", "TEAM_ABBREVIATION", "PLAYER_AGE", "GP", "GS", "RANK_MIN", "RANK_FGM", "RANK_FGA", "RANK_FG_PCT", "RANK_FG3M", "RANK_FG3A", "RANK_FG3_PCT", "RANK_FTM", "RANK_FTA", "RANK_FT_PCT", "RANK_OREB", "RANK_DREB", "RANK_REB", "RANK_AST", "RANK_STL", "RANK_BLK", "RANK_TOV", "RANK_PTS", "RANK_EFF"], "rowSet": [[2584, "2004-05", "00", 1610612755, "PHI", "NR", "NR", "NR", 140, 123, 132, null, 80, 76, null, 89, 104, 6, 115, 140, 137, 123, 132, 130, 137, 119, 125], [2584, "2007-08", "00", 1610612755, "PHI", "NR", "NR", "NR", 101, 83, 89, 42, 91, 94, null, 93, 88, null, 127, 138, 138, 71, 70, 54, 71, 96, 116], [2584, "2008-09", "00", 1610612755, "PHI", "NR", "NR", "NR", 105, 89, 83, null, 66, 75, null, 158, 145, null, 170, 138, 149, 92, 165, 96, 103, 102, 129], [2584, "2010-11", "00", 1610612740, "NOH", "NR", "NR", "NR", 132, 112, 109, null, 89, 86, null, 120, 120, null, 137, 155, 155, 114, 118, 131, 130, 117, 146], [2584, "2011-12", "00", 1610612737, "ATL", "NR", "NR", "NR", 146, 144, 152, null, 93, 98, null, 161, 167, null, 148, 143, 151, 125, 161, 139, 149, 150, 152], [2584, "2012-13", "00", 1610612746, "LAC", "NR", "NR", "NR", 178, 171, 187, null, 112, 131, null, 138, 147, null, 172, 161, 172, 144, 137, 146, 184, 171, 160], [2584, "2013-14", "00", 1610612746, "LAC", "NR", "NR", "NR", 173, 175, 171, null, 108, 115, null, 149, 157, null, 173, 141, 157, 157, 103, 132, 154, 172, 162]]}]}, {"resource": "commonplayerinfo", "parameters": [{"PlayerID": 2584}, {"LeagueID": null}], "resultSets": [{"name": "CommonPlayerInfo", "headers": ["PERSON_ID", "FIRST_NAME", "LAST_NAME", "DISPLAY_FIRST_LAST", "DISPLAY_LAST_COMMA_FIRST", "DISPLAY_FI_LAST", "PLAYER_SLUG", "BIRTHDATE", "SCHOOL", "COUNTRY", "LAST_AFFILIATION", "HEIGHT", "WEIGHT", "SEASON_EXP", "JERSEY", "POSITION", "ROSTERSTATUS", "GAMES_PLAYED_CURRENT_SEASON_FLAG", "TEAM_ID", "TEAM_NAME", "TEAM_ABBREVIATION", "TEAM_CODE", "TEAM_CITY", "PLAYERCODE", "FROM_YEAR", "TO_YEAR", "DLEAGUE_FLAG", "NBA_FLAG", "GAMES_PLAYED_FLAG", "DRAFT_YEAR", "DRAFT_ROUND", "DRAFT_NUMBER", "GREATEST_75_FLAG"], "rowSet": [[2584, "Willie", "Green", "Willie Green", "Green, Willie", "W. Green", "willie-green", "1981-07-28T00:00:00", "Detroit", "USA", "Detroit/USA", "6-3", "205", 12, "34", "Guard", "Inactive", "N", 1610612755, "76ers", "PHI", "sixers", "Philadelphia", "willie_green", 2003, 2014, "N", "Y", "Y", "2003", "2", "41", "N"]]}, {"name": "PlayerHeadlineStats", "headers": ["PLAYER_ID", "PLAYER_NAME", "TimeFrame", "PTS", "AST", "REB", "ALL_STAR_APPEARANCES"], "rowSet": [[2584, "Willie Green", "career", 8.3, 1.4, 1.8, 0]]}, {"name": "AvailableSeasons", "headers": ["SEASON_ID"], "rowSet": [["12003"], ["22003"], ["12004"], ["22004"], ["42004"], ["22005"], ["12006"], ["22006"], ["12007"], ["22007"], ["42007"], ["12008"], ["22008"], ["42008"], ["12009"], ["22009"], ["12010"], ["22010"], ["42010"], ["22011"], ["42011"], ["12012"], ["22012"], ["42012"], ["12013"], ["22013"], ["42013"], ["12014"], ["22014"]]}]}]