[{"resource": "playercareerstats", "parameters": {"PerMode": "Totals", "PlayerID": 77579, "LeagueID": null}, "resultSets": [{"name": "SeasonTotalsRegularSeason", "headers": ["PLAYER_ID", "SEASON_ID", "LEAGUE_ID", "TEAM_ID", "TEAM_ABBREVIATION", "PLAYER_AGE", "GP", "GS", "MIN", "FGM", "FGA", "FG_PCT", "FG3M", "FG3A", "FG3_PCT", "FTM", "FTA", "FT_PCT", "OREB", "DREB", "REB", "AST", "STL", "BLK", "TOV", "PF", "PTS"], "rowSet": [[77579, "1955-56", "00", 1610612747, "MNL", 23.0, 69, null, 973.0, 120, 375, 0.32, null, null, null, 78, 96, 0.813, null, null, 110, 132, null, null, null, 74, 318], [77579, "1956-57", "00", 1610612747, "MNL", 24.0, 72, null, 1848.0, 243, 688, 0.353, null, null, null, 179, 240, 0.746, null, null, 237, 201, null, null, null, 95, 665]]}, {"name": "CareerTotalsRegularSeason", "headers": ["PLAYER_ID", "LEAGUE_ID", "Team_ID", "GP", "GS", "MIN", "FGM", "FGA", "FG_PCT", "FG3M", "FG3A", "FG3_PCT", "FTM", "FTA", "FT_PCT", "OREB", "DREB", "REB", "AST", "STL", "BLK", "TOV", "PF", "PTS"], "rowSet": [[77579, "00", 0, 141, null, 2821.0, 363, 1063, 0.341486, null, null, null, 257, 336, 0.76488, null, null, 347, 333, null, null, null, 169, 983]]}, {"name": "SeasonTotalsPostSeason", "headers": ["PLAYER_ID", "SEASON_ID", "LEAGUE_ID", "TEAM_ID", "TEAM_ABBREVIATION", "PLAYER_AGE", "GP", "GS", "MIN", "FGM", "FGA", "FG_PCT", "FG3M", "FG3A", "FG3_PCT", "FTM", "FTA", "FT_PCT", "OREB", "DREB", "REB", "AST", "STL", "BLK", "TOV", "PF", "PTS"], "rowSet": [[77579, "1955-56", "00", 1610612747, "MNL", 23.0, 3, null, 52.0, 10, 19, 0.526, null, null, null, 6, 7, 0.857, null, null, 5, 8, null, null, null, 4, 26], [77579, "1956-57", "00", 1610612747, "MNL", 24.0, 5, null, 98.0, 9, 36, 0.25, null, null, null, 7, 9, 0.778, null, null, 13, 6, null, null, null, 7, 25]]}, {"name": "CareerTotalsPostSeason", "headers": ["PLAYER_ID", "LEAGUE_ID", "Team_ID", "GP", "GS", "MIN", "FGM", "FGA", "FG_PCT", "FG3M", "FG3A", "FG3_PCT", "FTM", "FTA", "FT_PCT", "OREB", "DREB", "REB", "AST", "STL", "BLK", "TOV", "PF", "PTS"], "rowSet": [[77579, "00", 0, 8, null, 150.0, 19, 55, 0.345454, null, null, null, 13, 16, 0.8125, null, null, 18, 14, null, null, null, 11, 51]]}, {"name": "SeasonTotalsAllStarSeason", "headers": ["PLAYER_ID", "SEASON_ID", "LEAGUE_ID", "TEAM_ID", "TEAM_ABBREVIATION", "PLAYER_AGE", "GP", "GS", "MIN", "FGM", "FGA", "FG_PCT", "FG3M", "FG3A", "FG3_PCT", "FTM", "FTA", "FT_PCT", "OREB", "DREB", "REB", "AST", "STL", "BLK", "TOV", "PF", "PTS"], "rowSet": []}, {"name": "CareerTotalsAllStarSeason", "headers": ["PLAYER_ID", "LEAGUE_ID", "Team_ID", "GP", "GS", "MIN", "FGM", "FGA", "FG_PCT", "FG3M", "FG3A", "FG3_PCT", "FTM", "FTA", "FT_PCT", "OREB", "DREB", "REB", "AST", "STL", "BLK", "TOV", "PF", "PTS"], "rowSet": []}, {"name": "SeasonTotalsCollegeSeason", "headers": ["PLAYER_ID", "SEASON_ID", "LEAGUE_ID", "ORGANIZATION_ID", "SCHOOL_NAME", "PLAYER_AGE", "GP", "GS", "MIN", "FGM", "FGA", "FG_PCT", "FG3M", "FG3A", "FG3_PCT", "FTM", "FTA", "FT_PCT", "OREB", "DREB", "REB", "AST", "STL", "BLK", "TOV", "PF", "PTS"], "rowSet": []}, {"name": "CareerTotalsCollegeSeason", "headers": ["PLAYER_ID", "LEAGUE_ID", "ORGANIZATION_ID", "GP", "GS", "MIN", "FGM", "FGA", "FG_PCT", "FG3M", "FG3A", "FG3_PCT", "FTM", "FTA", "FT_PCT", "OREB", "DREB", "REB", "AST", "STL", "BLK", "TOV", "PF", "PTS"], "rowSet": []}, {"name": "SeasonTotalsShowcaseSeason", "headers": ["PLAYER_ID", "SEASON_ID", "LEAGUE_ID", "TEAM_ID", "TEAM_ABBREVIATION", "PLAYER_AGE", "GP", "GS", "MIN", "FGM", "FGA", "FG_PCT", "FG3M", "FG3A", "FG3_PCT", "FTM", "FTA", "FT_PCT", "OREB", "DREB", "REB", "AST", "STL", "BLK", "TOV", "PF", "PTS"], "rowSet": []}, {"name": "CareerTotalsShowcaseSeason", "headers": ["PLAYER_ID", "LEAGUE_ID", "Team_ID", "GP", "GS", "MIN", "FGM", "FGA", "FG_PCT", "FG3M", "FG3A", "FG3_PCT", "FTM", "FTA", "FT_PCT", "OREB", "DREB", "REB", "AST", "STL", "BLK", "TOV", "PF", "PTS"], "rowSet": []}, {"name": "SeasonRankingsRegularSeason", "headers": ["PLAYER_ID", "SEASON_ID", "LEAGUE_ID", "TEAM_ID", "TEAM_ABBREVIATION", "PLAYER_AGE", "GP", "GS", "RANK_MIN", "RANK_FGM", "RANK_FGA", "RANK_FG_PCT", "RANK_FG3M", "RANK_FG3A", "RANK_FG3_PCT", "RANK_FTM", "RANK_FTA", "RANK_FT_PCT", "RANK_OREB", "RANK_DREB", "RANK_REB", "RANK_AST", "RANK_STL", "RANK_BLK", "RANK_TOV", "RANK_PTS", "RANK_EFF"], "rowSet": [[77579, "1955-56", "00", 1610612747, "MNL", "NR", "NR", "NR", 67, 70, 62, null, null, null, null, 68, 72, null, null, null, 76, 48, null, null, null, 69, 1], [77579, "1956-57", "00", 1610612747, "MNL", "NR", "NR", "NR", 35, 38, 35, null, null, null, null, 34, 34, 32, null, null, 56, 17, null, null, null, 39, 1]]}, {"name": "SeasonRankingsPostSeason", "headers": ["PLAYER_ID", "SEASON_ID", "LEAGUE_ID", "TEAM_ID", "TEAM_ABBREVIATION", "PLAYER_AGE", "GP", "GS", "RANK_MIN", "RANK_FGM", "RANK_FGA", "RANK_FG_PCT", "RANK_FG3M", "RANK_FG3A", "RANK_FG3_PCT", "RANK_FTM", "RANK_FTA", "RANK_FT_PCT", "RANK_OREB", "RANK_DREB", "RANK_REB", "RANK_AST", "RANK_STL", "RANK_BLK", "RANK_TOV", "RANK_PTS", "RANK_EFF"], "rowSet": [[77579, "1955-56", "00", 1610612747, "MNL", "NR", "NR", "NR", 53, 46, 54, null, null, null, null, 49, 52, 9, null, null, 58, 40, null, null, null, 50, 1], [77579, "1956-57", "00", 1610612747, "MNL", "NR", "NR", "NR", 28, 37, 33, null, null, null, null, 34, 37, null, null, null, 40, 32, null, null, null, 38, 1]]}]}, {"resource": "commonplayerinfo", "parameters": [{"PlayerID": 77579}, {"LeagueID": null}], "resultSets": [{"name": "CommonPlayerInfo", "headers": ["PERSON_ID", "FIRST_NAME", "LAST_NAME", "DISPLAY_FIRST_LAST", "DISPLAY_LAST_COMMA_FIRST", "DISPLAY_FI_LAST", "PLAYER_SLUG", "BIRTHDATE", "SCHOOL", "COUNTRY", "LAST_AFFILIATION", "HEIGHT", "WEIGHT", "SEASON_EXP", "JERSEY", "POSITION", "ROSTERSTATUS", "GAMES_PLAYED_CURRENT_SEASON_FLAG", "TEAM_ID", "TEAM_NAME", "TEAM_ABBREVIATION", "TEAM_CODE", "TEAM_CITY", "PLAYERCODE", "FROM_YEAR", "TO_YEAR", "DLEAGUE_FLAG", "NBA_FLAG", "GAMES_PLAYED_FLAG", "DRAFT_YEAR", "DRAFT_ROUND", "DRAFT_NUMBER", "GREATEST_75_FLAG"], "rowSet": [[77579, "Chuck", "Mencel", "Chuck Mencel", "Mencel, Chuck", "C. Mencel", "chuck-mencel", "1933-04-21T00:00:00", "Minnesota", "USA", "Minnesota/USA", "6-0", "168", 2, "18", "Guard", "Inactive", "N", 1610612747, "Lakers", "MNL", "lakers", "Minneapolis", "HISTADD_chuck_mencel", 1955, 1956, "N", "Y", "Y", "1955", "2", "12", "N"]]}, {"name": "PlayerHeadlineStats", "headers": ["PLAYER_ID", "PLAYER_NAME", "TimeFrame", "PTS", "AST", "REB", "ALL_STAR_APPEARANCES"], "rowSet": [[77579, "Chuck Mencel", "career", 7.0, 2.4, 2.5, 0]]}, {"name": "AvailableSeasons", "headers": ["SEASON_ID"], "rowSet": [["21955"], ["41955"], ["21956"], ["41956"]]}]}]