[{"resource": "playercareerstats", "parameters": {"PerMode": "Totals", "PlayerID": 78414, "LeagueID": null}, "resultSets": [{"name": "SeasonTotalsRegularSeason", "headers": ["PLAYER_ID", "SEASON_ID", "LEAGUE_ID", "TEAM_ID", "TEAM_ABBREVIATION", "PLAYER_AGE", "GP", "GS", "MIN", "FGM", "FGA", "FG_PCT", "FG3M", "FG3A", "FG3_PCT", "FTM", "FTA", "FT_PCT", "OREB", "DREB", "REB", "AST", "STL", "BLK", "TOV", "PF", "PTS"], "rowSet": [[78414, "1981-82", "00", 1610612757, "POR", 23.0, 71, 22, 1207.0, 149, 296, 0.503, 0, 0, null, 51, 72, 0.708, 106, 148, 254, 52, 42, 22, 55, 215, 349], [78414, "1982-83", "00", 1610612757, "POR", 24.0, 48, 0, 527.0, 87, 171, 0.509, 0, 1, 0.0, 21, 31, 0.677, 44, 52, 96, 32, 18, 9, 40, 95, 195], [78414, "1983-84", "00", 1610612757, "POR", 25.0, 43, 0, 327.0, 50, 100, 0.5, 0, 1, 0.0, 17, 25, 0.68, 27, 34, 61, 20, 22, 11, 21, 75, 117], [78414, "1984-85", "00", 1610612758, "KCK", 26.0, 54, 0, 366.0, 51, 108, 0.472, 0, 0, null, 21, 25, 0.84, 28, 35, 63, 17, 15, 7, 20, 85, 123], [78414, "1985-86", "00", 1610612744, "GOS", 27.0, 61, 5, 749.0, 90, 167, 0.539, 1, 2, 0.5, 25, 43, 0.581, 65, 95, 160, 29, 29, 17, 30, 141, 206], [78414, "1986-87", "00", 1610612754, "IND", 28.0, 5, 0, 44.0, 5, 14, 0.357, 0, 0, 0.0, 0, 0, 0.0, 2, 5, 7, 2, 2, 1, 0, 11, 10]]}, {"name": "CareerTotalsRegularSeason", "headers": ["PLAYER_ID", "LEAGUE_ID", "Team_ID", "GP", "GS", "MIN", "FGM", "FGA", "FG_PCT", "FG3M", "FG3A", "FG3_PCT", "FTM", "FTA", "FT_PCT", "OREB", "DREB", "REB", "AST", "STL", "BLK", "TOV", "PF", "PTS"], "rowSet": [[78414, "00", 0, 282, 27, 3220.0, 432, 856, 0.504672, 1, 4, 0.25, 135, 196, 0.688775, 272, 369, 641, 152, 128, 67, 166, 622, 1000]]}, {"name": "SeasonTotalsPostSeason", "headers": ["PLAYER_ID", "SEASON_ID", "LEAGUE_ID", "TEAM_ID", "TEAM_ABBREVIATION", "PLAYER_AGE", "GP", "GS", "MIN", "FGM", "FGA", "FG_PCT", "FG3M", "FG3A", "FG3_PCT", "FTM", "FTA", "FT_PCT", "OREB", "DREB", "REB", "AST", "STL", "BLK", "TOV", "PF", "PTS"], "rowSet": [[78414, "1983-84", "00", 1610612757, "POR", 25.0, 3, 0, 19.0, 0, 0, 0.0, 0, 0, 0.0, 2, 2, 1.0, 0, 0, 0, 0, 1, 0, 1, 10, 2]]}, {"name": "CareerTotalsPostSeason", "headers": ["PLAYER_ID", "LEAGUE_ID", "Team_ID", "GP", "GS", "MIN", "FGM", "FGA", "FG_PCT", "FG3M", "FG3A", "FG3_PCT", "FTM", "FTA", "FT_PCT", "OREB", "DREB", "REB", "AST", "STL", "BLK", "TOV", "PF", "PTS"], "rowSet": [[78414, "00", 0, 3, 0, 19.0, 0, 0, 0.0, 0, 0, 0.0, 2, 2, 1.0, 0, 0, 0, 0, 1, 0, 1, 10, 2]]}, {"name": "SeasonTotalsAllStarSeason", "headers": ["PLAYER_ID", "SEASON_ID", "LEAGUE_ID", "TEAM_ID", "TEAM_ABBREVIATION", "PLAYER_AGE", "GP", "GS", "MIN", "FGM", "FGA", "FG_PCT", "FG3M", "FG3A", "FG3_PCT", "FTM", "FTA", "FT_PCT", "OREB", "DREB", "REB", "AST", "STL", "BLK", "TOV", "PF", "PTS"], "rowSet": []}, {"name": "CareerTotalsAllStarSeason", "headers": ["PLAYER_ID", "LEAGUE_ID", "Team_ID", "GP", "GS", "MIN", "FGM", "FGA", "FG_PCT", "FG3M", "FG3A", "FG3_PCT", "FTM", "FTA", "FT_PCT", "OREB", "DREB", "REB", "AST", "STL", "BLK", "TOV", "PF", "PTS"], "rowSet": []}, {"name": "SeasonTotalsCollegeSeason", "headers": ["PLAYER_ID", "SEASON_ID", "LEAGUE_ID", "ORGANIZATION_ID", "SCHOOL_NAME", "PLAYER_AGE", "GP", "GS", "MIN", "FGM", "FGA", "FG_PCT", "FG3M", "FG3A", "FG3_PCT", "FTM", "FTA", "FT_PCT", "OREB", "DREB", "REB", "AST", "STL", "BLK", "TOV", "PF", "PTS"], "rowSet": []}, {"name": "CareerTotalsCollegeSeason", "headers": ["PLAYER_ID", "LEAGUE_ID", "ORGANIZATION_ID", "GP", "GS", "MIN", "FGM", "FGA", "FG_PCT", "FG3M", "FG3A", "FG3_PCT", "FTM", "FTA", "FT_PCT", "OREB", "DREB", "REB", "AST", "STL", "BLK", "TOV", "PF", "PTS"], "rowSet": []}, {"name": "SeasonTotalsShowcaseSeason", "headers": ["PLAYER_ID", "SEASON_ID", "LEAGUE_ID", "TEAM_ID", "TEAM_ABBREVIATION", "PLAYER_AGE", "GP", "GS", "MIN", "FGM", "FGA", "FG_PCT", "FG3M", "FG3A", "FG3_PCT", "FTM", "FTA", "FT_PCT", "OREB", "DREB", "REB", "AST", "STL", "BLK", "TOV", "PF", "PTS"], "rowSet": []}, {"name": "CareerTotalsShowcaseSeason", "headers": ["PLAYER_ID", "LEAGUE_ID", "Team_ID", "GP", "GS", "MIN", "FGM", "FGA", "FG_PCT", "FG3M", "FG3A", "FG3_PCT", "FTM", "FTA", "FT_PCT", "OREB", "DREB", "REB", "AST", "STL", "BLK", "TOV", "PF", "PTS"], "rowSet": []}, {"name": "SeasonRankingsRegularSeason", "headers": ["PLAYER_ID", "SEASON_ID", "LEAGUE_ID", "TEAM_ID", "TEAM_ABBREVIATION", "PLAYER_AGE", "GP", "GS", "RANK_MIN", "RANK_FGM", "RANK_FGA", "RANK_FG_PCT", "RANK_FG3M", "RANK_FG3A", "RANK_FG3_PCT", "RANK_FTM", "RANK_FTA", "RANK_FT_PCT", "RANK_OREB", "RANK_DREB", "RANK_REB", "RANK_AST", "RANK_STL", "RANK_BLK", "RANK_TOV", "RANK_PTS", "RANK_EFF"], "rowSet": [[78414, "1981-82", "00", 1610612757, "POR", "NR", "NR", "NR", 177, 196, 200, null, 152, 250, null, 215, 218, null, 111, 138, 125, 221, 156, 131, 217, 202, 191], [78414, "1982-83", "00", 1610612757, "POR", "NR", "NR", "NR", 244, 235, 245, null, 149, 216, null, 258, 261, null, 193, 244, 231, 254, 243, 191, 247, 241, 239], [78414, "1983-84", "00", 1610612757, "POR", "NR", "NR", "NR", 265, 256, 260, null, 163, 214, null, 262, 268, null, 237, 264, 256, 265, 222, 180, 264, 260, 256], [78414, "1984-85", "00", 1610612758, "KCK", "NR", "NR", "NR", 265, 261, 262, null, 148, 263, null, 267, 273, null, 235, 260, 254, 272, 247, 212, 271, 263, 260], [78414, "1985-86", "00", 1610612744, "GOS", "NR", "NR", "NR", 223, 235, 249, null, 132, 198, null, 257, 253, null, 163, 196, 184, 248, 204, 141, 255, 239, 220], [78414, "1986-87", "00", 1610612754, "IND", "NR", "NR", "NR", 316, 315, 314, null, 167, 278, null, 326, 328, null, 314, 309, 315, 311, 301, 287, 331, 321, 318]]}, {"name": "SeasonRankingsPostSeason", "headers": ["PLAYER_ID", "SEASON_ID", "LEAGUE_ID", "TEAM_ID", "TEAM_ABBREVIATION", "PLAYER_AGE", "GP", "GS", "RANK_MIN", "RANK_FGM", "RANK_FGA", "RANK_FG_PCT", "RANK_FG3M", "RANK_FG3A", "RANK_FG3_PCT", "RANK_FTM", "RANK_FTA", "RANK_FT_PCT", "RANK_OREB", "RANK_DREB", "RANK_REB", "RANK_AST", "RANK_STL", "RANK_BLK", "RANK_TOV", "RANK_PTS", "RANK_EFF"], "rowSet": [[78414, "1983-84", "00", 1610612757, "POR", "NR", "NR", "NR", 165, 177, 182, null, 53, 102, null, 144, 147, null, 167, 169, 174, 171, 125, 129, 161, 174, 170]]}]}, {"resource": "commonplayerinfo", "parameters": [{"PlayerID": 78414}, {"LeagueID": null}], "resultSets": [{"name": "CommonPlayerInfo", "headers": ["PERSON_ID", "FIRST_NAME", "LAST_NAME", "DISPLAY_FIRST_LAST", "DISPLAY_LAST_COMMA_FIRST", "DISPLAY_FI_LAST", "PLAYER_SLUG", "BIRTHDATE", "SCHOOL", "COUNTRY", "LAST_AFFILIATION", "HEIGHT", "WEIGHT", "SEASON_EXP", "JERSEY", "POSITION", "ROSTERSTATUS", "GAMES_PLAYED_CURRENT_SEASON_FLAG", "TEAM_ID", "TEAM_NAME", "TEAM_ABBREVIATION", "TEAM_CODE", "TEAM_CITY", "PLAYERCODE", "FROM_YEAR", "TO_YEAR", "DLEAGUE_FLAG", "NBA_FLAG", "GAMES_PLAYED_FLAG", "DRAFT_YEAR", "DRAFT_ROUND", "DRAFT_NUMBER", "GREATEST_75_FLAG"], "rowSet": [[78414, "Peter", "Verhoeven", "Peter Verhoeven", "Verhoeven, Peter", "P. Verhoeven", "peter-verhoeven", "1959-02-15T00:00:00", "Fresno State", "USA", "Fresno State/USA", "6-9", "215", 6, "50", "Forward", "Inactive", "N", 1610612757, "Trail Blazers", "POR", "blazers", "Portland", "HISTADD_peter_verhoeven", 1981, 1986, "N", "Y", "Y", "1981", "4", "85", "N"]]}, {"name": "PlayerHeadlineStats", "headers": ["PLAYER_ID", "PLAYER_NAME", "TimeFrame", "PTS", "AST", "REB", "ALL_STAR_APPEARANCES"], "rowSet": [[78414, "Peter Verhoeven", "career", 3.5, 0.5, 2.3, 0]]}, {"name": "AvailableSeasons", "headers": ["SEASON_ID"], "rowSet": [["21981"], ["21982"], ["21983"], ["41983"], ["21984"], ["21985"], ["21986"]]}]}]